setup.cfg
setup.py
SplitWavePy.egg-info/PKG-INFO
SplitWavePy.egg-info/SOURCES.txt
SplitWavePy.egg-info/dependency_links.txt
SplitWavePy.egg-info/requires.txt
SplitWavePy.egg-info/top_level.txt
splitwavepy/__init__.py
splitwavepy/core/__init__.py
splitwavepy/core/core.py
splitwavepy/core/core3d.py
splitwavepy/core/data.py
splitwavepy/core/geom.py
splitwavepy/core/io.py
splitwavepy/core/pair.py
splitwavepy/core/trio.py
splitwavepy/core/window.py
splitwavepy/eigval/eigval3d.py
splitwavepy/measure/__init__.py
splitwavepy/measure/bootstrap.py
splitwavepy/measure/crossM.py
splitwavepy/measure/eig3dM.py
splitwavepy/measure/eigenM.py
splitwavepy/measure/measure.py
splitwavepy/measure/stack.py
splitwavepy/measure/transM.py
splitwavepy/measure/xconvM.py
tests/__init__.py
tests/test_core.py
tests/test_io.py