Metadata-Version: 1.0
Name: SplitWavePy
Version: 0.3.0
Summary: Shearwave splitting measurement tools
Home-page: https://github.com/JackWalpole/splitwavepy
Author: Jack Walpole
Author-email: j.walpole@gmail.com
License: MIT
Keywords: shear wave splitting seismic anisotropy seismology
Platform: UNKNOWN
